qtpynodeeditor/DefaultStyle.json
qtpynodeeditor/__init__.py
qtpynodeeditor/_version.py
qtpynodeeditor/base.py
qtpynodeeditor/connection.py
qtpynodeeditor/connection_geometry.py
qtpynodeeditor/connection_graphics_object.py
qtpynodeeditor/connection_painter.py
qtpynodeeditor/data_model_registry.py
qtpynodeeditor/enums.py
qtpynodeeditor/exceptions.py
qtpynodeeditor/flow_scene.py
qtpynodeeditor/flow_view.py
qtpynodeeditor/node.py
qtpynodeeditor/node_connection_interaction.py
qtpynodeeditor/node_data.py
qtpynodeeditor/node_geometry.py
qtpynodeeditor/node_graphics_object.py
qtpynodeeditor/node_painter.py
qtpynodeeditor/node_state.py
qtpynodeeditor/port.py
qtpynodeeditor/style.py
qtpynodeeditor/type_converter.py
qtpynodeeditor/version.py
qtpynodeeditor/examples/__init__.py
qtpynodeeditor/examples/calculator.py
qtpynodeeditor/examples/connection_colors.py
qtpynodeeditor/examples/image.py
qtpynodeeditor/examples/style.py
qtpynodeeditor/tests/__init__.py
qtpynodeeditor/tests/conftest.py
qtpynodeeditor/tests/test_basic.py
qtpynodeeditor/tests/test_examples.py
qtpynodeeditor-0.3.3.dist-info/AUTHORS.rst
qtpynodeeditor-0.3.3.dist-info/LICENSE
qtpynodeeditor-0.3.3.dist-info/METADATA
qtpynodeeditor-0.3.3.dist-info/WHEEL
qtpynodeeditor-0.3.3.dist-info/top_level.txt
qtpynodeeditor-0.3.3.dist-info/RECORD
