Metadata-Version: 2.1
Name: qtpynodeeditor
Version: 0.3.3
Summary: Python Qt node editor
Author: Ken Lauer
License: Copyright (c) 2019, Ken Lauer
Classifier: Development Status :: 2 - Pre-Alpha
Classifier: Natural Language :: English
Classifier: Programming Language :: Python :: 3
Requires-Python: >=3.9
License-File: LICENSE
License-File: AUTHORS.rst
Requires-Dist: qtpy
Provides-Extra: pyqt
Requires-Dist: PyQt6; extra == "pyqt"
Provides-Extra: pyqt5
Requires-Dist: PyQt5; extra == "pyqt5"
Provides-Extra: pyqt6
Requires-Dist: PyQt6; extra == "pyqt6"
Provides-Extra: pyside
Requires-Dist: PySide6; extra == "pyside"
Provides-Extra: pyside6
Requires-Dist: PySide6; extra == "pyside6"
Provides-Extra: test
Requires-Dist: pytest; extra == "test"
Requires-Dist: pytest-qt; extra == "test"
Requires-Dist: pytest-cov; extra == "test"
Provides-Extra: doc
Requires-Dist: sphinx; extra == "doc"
Requires-Dist: ipython; extra == "doc"
Requires-Dist: numpydoc; extra == "doc"
Requires-Dist: sphinx-copybutton; extra == "doc"
Requires-Dist: sphinx_rtd_theme; extra == "doc"
Requires-Dist: sphinxcontrib-jquery; extra == "doc"
